{
  "lastUpdated": 1779163661629,
  "servers": [
    {
      "id": "srv-smartface",
      "name": "Smartface",
      "location": "Utkal Alumina",
      "status": "degraded",
      "cpu": 42,
      "memory": 66,
      "disk": 69,
      "backupStatus": "successful",
      "history": [
        48,
        44,
        49,
        52,
        52,
        54,
        57,
        55,
        55,
        60,
        61,
        58,
        57,
        55,
        54,
        53,
        50,
        46,
        41,
        42
      ]
    },
    {
      "id": "srv-clms",
      "name": "CLMS",
      "location": "Utkal Alumina",
      "status": "degraded",
      "cpu": 48,
      "memory": 57,
      "disk": 80,
      "backupStatus": "successful",
      "history": [
        46,
        46,
        42,
        43,
        41,
        45,
        48,
        43,
        44,
        40,
        45,
        47,
        51,
        46,
        46,
        48,
        45,
        48,
        51,
        48
      ]
    },
    {
      "id": "srv-dhcp",
      "name": "DHCP",
      "location": "Utkal Alumina",
      "status": "degraded",
      "cpu": 16,
      "memory": 74,
      "disk": 48,
      "backupStatus": "failed",
      "history": [
        14,
        15,
        10,
        14,
        13,
        17,
        12,
        11,
        13,
        11,
        16,
        19,
        22,
        27,
        27,
        23,
        18,
        18,
        19,
        16
      ]
    },
    {
      "id": "srv-ilms-app",
      "name": "ILMS APP",
      "location": "Utkal Alumina",
      "status": "operational",
      "cpu": 54,
      "memory": 59,
      "disk": 85,
      "backupStatus": "successful",
      "history": [
        75,
        78,
        78,
        76,
        76,
        74,
        69,
        72,
        73,
        72,
        67,
        70,
        67,
        66,
        62,
        59,
        55,
        54,
        53,
        54
      ]
    },
    {
      "id": "srv-ilms-db",
      "name": "ILMS DB",
      "location": "Utkal Alumina",
      "status": "degraded",
      "cpu": 62,
      "memory": 47,
      "disk": 100,
      "backupStatus": "failed",
      "history": [
        50,
        45,
        44,
        49,
        54,
        53,
        54,
        52,
        50,
        52,
        53,
        55,
        56,
        51,
        55,
        60,
        58,
        62,
        66,
        62
      ]
    }
  ],
  "networks": [
    {
      "id": "net-rjio",
      "provider": "RJIO",
      "status": "operational",
      "uptime": 99.99,
      "latency": 20,
      "utilization": 26,
      "history": [
        21,
        22,
        16,
        22,
        20,
        17,
        17,
        19,
        15,
        12,
        19,
        22,
        15,
        20,
        22,
        21,
        21,
        24,
        31,
        26
      ]
    },
    {
      "id": "net-railtel",
      "provider": "RailTel",
      "status": "operational",
      "uptime": 99.92,
      "latency": 8,
      "utilization": 23,
      "history": [
        41,
        37,
        31,
        31,
        37,
        35,
        29,
        35,
        36,
        41,
        35,
        40,
        33,
        26,
        33,
        27,
        20,
        26,
        24,
        23
      ]
    }
  ],
  "configs": {
    "nutanix": {
      "connected": true,
      "endpoint": "10.20.40.12",
      "username": "nutanix_admin",
      "authMethod": "SSH Key"
    },
    "symphony": {
      "connected": true,
      "endpoint": "https://summit.internal/api/v2",
      "username": "symphony_agent",
      "authMethod": "API Key"
    },
    "isms": {
      "connected": true,
      "endpoint": "https://apex.internal/ords/isms",
      "username": "apex_oauth",
      "authMethod": "OAuth Client"
    },
    "compliance": {
      "connected": true,
      "endpoint": "https://apex.internal/ords/compliance",
      "username": "apex_compliance",
      "authMethod": "OAuth Client"
    }
  },
  "nutanix": {
    "uptime": "142d 8h 12m",
    "nodesCount": 6,
    "storageUsage": 100,
    "historyCpu": [
      44,
      43,
      47,
      43,
      45,
      46,
      46,
      47,
      45,
      46,
      44,
      48,
      51,
      51,
      49,
      47,
      45,
      49,
      48,
      46
    ],
    "historyMem": [
      66,
      65,
      64,
      65,
      63,
      65,
      64,
      63,
      63,
      62,
      64,
      63,
      62,
      64,
      66,
      67,
      69,
      68,
      68,
      66
    ]
  },
  "symphony": {
    "openIncidents": 0,
    "serviceRequests": 20,
    "workOrders": 11,
    "changeRequests": 0,
    "serviceRequestsSla": 97
  },
  "isms": [
    {
      "id": "isms-risk",
      "name": "Annual Risk Assessments",
      "progress": 100,
      "target": 100
    },
    {
      "id": "isms-train",
      "name": "Staff Security Awareness",
      "progress": 100,
      "target": 100
    },
    {
      "id": "isms-audit",
      "name": "Internal Audit Resolved",
      "progress": 100,
      "target": 100
    },
    {
      "id": "isms-inc",
      "name": "Incident Response Drills",
      "progress": 72,
      "target": 100
    }
  ],
  "compliance": {
    "serverOs": 92,
    "serverPatch": 99,
    "endpointCsClient": 96,
    "endpointCsPatch": 98,
    "endpointIntuneClient": 99,
    "endpointIntunePatch": 95,
    "endpointClearpass": 91,
    "endpointSupportedOs": 97,
    "endpointSamAgent": 96,
    "endpointHsd": 97,
    "endpointDomain": 91,
    "endpointBitlocker": 91,
    "endpointAverage": 95.2
  }
}