{
  "lastUpdated": 1779210290257,
  "servers": [
    {
      "id": "srv-smartface",
      "name": "Smartface",
      "location": "Utkal Alumina",
      "status": "degraded",
      "cpu": 97,
      "memory": 23,
      "disk": 56,
      "backupStatus": "successful",
      "history": [
        99,
        97,
        98,
        96,
        95,
        97,
        97,
        97,
        99,
        99,
        96,
        99,
        99,
        99,
        99,
        94,
        93,
        98,
        99,
        97
      ]
    },
    {
      "id": "srv-clms",
      "name": "CLMS",
      "location": "Utkal Alumina",
      "status": "degraded",
      "cpu": 78,
      "memory": 53,
      "disk": 75,
      "backupStatus": "successful",
      "history": [
        81,
        85,
        80,
        77,
        76,
        78,
        74,
        79,
        76,
        81,
        81,
        85,
        88,
        85,
        88,
        86,
        84,
        87,
        83,
        78
      ]
    },
    {
      "id": "srv-dhcp",
      "name": "DHCP",
      "location": "Utkal Alumina",
      "status": "operational",
      "cpu": 49,
      "memory": 20,
      "disk": 37,
      "backupStatus": "successful",
      "history": [
        48,
        45,
        50,
        48,
        48,
        44,
        40,
        44,
        49,
        44,
        49,
        48,
        43,
        40,
        42,
        40,
        41,
        44,
        44,
        49
      ]
    },
    {
      "id": "srv-ilms-app",
      "name": "ILMS APP",
      "location": "Utkal Alumina",
      "status": "degraded",
      "cpu": 50,
      "memory": 99,
      "disk": 79,
      "backupStatus": "successful",
      "history": [
        61,
        63,
        60,
        56,
        52,
        50,
        45,
        46,
        47,
        44,
        47,
        45,
        40,
        44,
        42,
        47,
        46,
        48,
        51,
        50
      ]
    },
    {
      "id": "srv-ilms-db",
      "name": "ILMS DB",
      "location": "Utkal Alumina",
      "status": "degraded",
      "cpu": 55,
      "memory": 52,
      "disk": 100,
      "backupStatus": "successful",
      "history": [
        87,
        92,
        89,
        84,
        83,
        88,
        84,
        82,
        80,
        75,
        80,
        79,
        76,
        73,
        69,
        64,
        62,
        57,
        55,
        55
      ]
    },
    {
      "id": "srv-ad-01",
      "name": "AD Primary",
      "location": "Utkal Alumina",
      "status": "operational",
      "cpu": 63,
      "memory": 28,
      "disk": 55,
      "backupStatus": "failed",
      "history": [
        68,
        71,
        76,
        73,
        72,
        75,
        79,
        80,
        84,
        81,
        81,
        82,
        85,
        80,
        77,
        72,
        70,
        68,
        67,
        63
      ]
    },
    {
      "id": "srv-ad-02",
      "name": "AD Backup",
      "location": "Utkal Alumina",
      "status": "degraded",
      "cpu": 10,
      "memory": 32,
      "disk": 47,
      "backupStatus": "successful",
      "history": [
        8,
        7,
        5,
        5,
        6,
        6,
        5,
        5,
        5,
        5,
        7,
        10,
        13,
        11,
        11,
        6,
        5,
        9,
        11,
        10
      ]
    },
    {
      "id": "srv-mail",
      "name": "Exchange Mail",
      "location": "Utkal Alumina",
      "status": "operational",
      "cpu": 7,
      "memory": 89,
      "disk": 85,
      "backupStatus": "successful",
      "history": [
        14,
        16,
        11,
        11,
        7,
        6,
        5,
        5,
        5,
        8,
        6,
        5,
        5,
        5,
        6,
        5,
        5,
        5,
        10,
        7
      ]
    },
    {
      "id": "srv-sap-app",
      "name": "SAP App",
      "location": "Utkal Alumina",
      "status": "degraded",
      "cpu": 7,
      "memory": 43,
      "disk": 87,
      "backupStatus": "failed",
      "history": [
        11,
        16,
        18,
        13,
        17,
        16,
        11,
        14,
        9,
        5,
        5,
        5,
        8,
        5,
        5,
        5,
        5,
        5,
        7,
        7
      ]
    },
    {
      "id": "srv-sap-db",
      "name": "SAP DB",
      "location": "Utkal Alumina",
      "status": "degraded",
      "cpu": 62,
      "memory": 86,
      "disk": 94,
      "backupStatus": "successful",
      "history": [
        59,
        62,
        61,
        64,
        69,
        65,
        64,
        59,
        61,
        61,
        58,
        62,
        67,
        70,
        66,
        64,
        65,
        62,
        66,
        62
      ]
    },
    {
      "id": "srv-utility",
      "name": "Utility Gateway",
      "location": "Utkal Alumina",
      "status": "operational",
      "cpu": 31,
      "memory": 68,
      "disk": 50,
      "backupStatus": "failed",
      "history": [
        13,
        11,
        13,
        15,
        17,
        21,
        26,
        21,
        22,
        21,
        20,
        16,
        18,
        21,
        24,
        27,
        23,
        24,
        27,
        31
      ]
    },
    {
      "id": "srv-fileshare",
      "name": "File Share",
      "location": "Utkal Alumina",
      "status": "degraded",
      "cpu": 18,
      "memory": 85,
      "disk": 98,
      "backupStatus": "successful",
      "history": [
        18,
        21,
        17,
        22,
        25,
        29,
        33,
        36,
        34,
        33,
        31,
        30,
        31,
        31,
        28,
        23,
        25,
        21,
        23,
        18
      ]
    },
    {
      "id": "srv-print",
      "name": "Print Server",
      "location": "Utkal Alumina",
      "status": "operational",
      "cpu": 10,
      "memory": 50,
      "disk": 46,
      "backupStatus": "successful",
      "history": [
        10,
        15,
        16,
        19,
        19,
        16,
        21,
        25,
        20,
        16,
        11,
        9,
        5,
        5,
        5,
        7,
        8,
        7,
        7,
        10
      ]
    },
    {
      "id": "srv-security",
      "name": "Endpoint Security",
      "location": "Utkal Alumina",
      "status": "degraded",
      "cpu": 29,
      "memory": 82,
      "disk": 70,
      "backupStatus": "failed",
      "history": [
        18,
        14,
        17,
        13,
        10,
        12,
        7,
        11,
        15,
        20,
        25,
        27,
        28,
        33,
        31,
        29,
        29,
        34,
        33,
        29
      ]
    },
    {
      "id": "srv-apex-db",
      "name": "Oracle APEX DB",
      "location": "Utkal Alumina",
      "status": "degraded",
      "cpu": 23,
      "memory": 52,
      "disk": 85,
      "backupStatus": "successful",
      "history": [
        51,
        48,
        45,
        41,
        37,
        41,
        37,
        34,
        30,
        33,
        30,
        26,
        25,
        24,
        28,
        26,
        23,
        21,
        26,
        23
      ]
    },
    {
      "id": "srv-cctv-01",
      "name": "CCTV Monitor 01",
      "location": "Utkal Alumina",
      "status": "operational",
      "cpu": 83,
      "memory": 70,
      "disk": 98,
      "backupStatus": "failed",
      "history": [
        77,
        74,
        77,
        73,
        78,
        79,
        84,
        81,
        83,
        87,
        86,
        82,
        77,
        82,
        83,
        82,
        83,
        81,
        84,
        83
      ]
    },
    {
      "id": "srv-cctv-02",
      "name": "CCTV Monitor 02",
      "location": "Utkal Alumina",
      "status": "operational",
      "cpu": 72,
      "memory": 53,
      "disk": 91,
      "backupStatus": "failed",
      "history": [
        99,
        97,
        99,
        98,
        99,
        99,
        98,
        93,
        88,
        85,
        80,
        81,
        84,
        87,
        84,
        81,
        76,
        76,
        72,
        72
      ]
    },
    {
      "id": "srv-weighbridge",
      "name": "Weighbridge Host",
      "location": "Utkal Alumina",
      "status": "degraded",
      "cpu": 5,
      "memory": 40,
      "disk": 38,
      "backupStatus": "successful",
      "history": [
        8,
        6,
        11,
        7,
        12,
        9,
        11,
        9,
        6,
        5,
        5,
        7,
        5,
        5,
        5,
        9,
        6,
        5,
        5,
        5
      ]
    },
    {
      "id": "srv-plm",
      "name": "PLM Server",
      "location": "Utkal Alumina",
      "status": "degraded",
      "cpu": 84,
      "memory": 25,
      "disk": 60,
      "backupStatus": "failed",
      "history": [
        99,
        99,
        99,
        99,
        99,
        95,
        99,
        94,
        99,
        98,
        97,
        99,
        99,
        95,
        92,
        96,
        94,
        94,
        89,
        84
      ]
    },
    {
      "id": "srv-backup-repo",
      "name": "Backup Repo",
      "location": "Utkal Alumina",
      "status": "degraded",
      "cpu": 16,
      "memory": 15,
      "disk": 100,
      "backupStatus": "successful",
      "history": [
        23,
        18,
        19,
        15,
        12,
        11,
        13,
        18,
        22,
        26,
        22,
        22,
        20,
        19,
        21,
        16,
        13,
        15,
        13,
        16
      ]
    }
  ],
  "networks": [
    {
      "id": "net-rjio",
      "provider": "RJIO",
      "status": "operational",
      "uptime": 99.99,
      "latency": 5,
      "utilization": 63,
      "history": [
        80,
        73,
        80,
        73,
        74,
        70,
        77,
        74,
        79,
        75,
        73,
        72,
        71,
        71,
        73,
        76,
        70,
        67,
        69,
        63
      ]
    },
    {
      "id": "net-railtel",
      "provider": "RailTel",
      "status": "degraded",
      "uptime": 99.92,
      "latency": 10,
      "utilization": 79,
      "history": [
        85,
        78,
        74,
        76,
        77,
        74,
        70,
        77,
        79,
        79,
        80,
        87,
        82,
        77,
        77,
        79,
        83,
        83,
        82,
        79
      ]
    }
  ],
  "configs": {
    "nutanix": {
      "connected": false,
      "endpoint": "",
      "username": "",
      "authMethod": "SSH Key"
    },
    "symphony": {
      "connected": true,
      "endpoint": "https://hsd.adityabirla.com/MDLIncidentMgmt/SDE_Dashboard.aspx",
      "username": "hil-dor.itdashboard@adityabirla.com",
      "authMethod": "API Key",
      "secret": "ItDa$(1857"
    },
    "solarwinds": {
      "connected": false,
      "endpoint": "",
      "username": "",
      "authMethod": "Basic Authentication"
    }
  },
  "nutanix": {
    "uptime": "142d 8h 12m",
    "nodesCount": 3,
    "storageUsage": 68,
    "historyCpu": [
      66,
      41,
      58,
      51,
      41,
      50,
      45,
      46,
      47,
      65,
      52,
      51,
      69,
      51,
      50,
      55,
      41,
      62,
      54,
      64
    ],
    "historyMem": [
      70,
      59,
      59,
      74,
      77,
      65,
      66,
      57,
      56,
      78,
      75,
      77,
      63,
      78,
      69,
      58,
      75,
      79,
      64,
      66
    ]
  },
  "symphony": {
    "openIncidents": 0,
    "openIncidentsBreakdown": {
      "new": 0,
      "assigned": 0,
      "inProgress": 0,
      "pending": 0
    },
    "serviceRequests": 0,
    "serviceRequestsBreakdown": {
      "new": 0,
      "assigned": 0,
      "inProgress": 0,
      "pending": 0
    },
    "workOrders": 0,
    "workOrdersBreakdown": {
      "new": 0,
      "assigned": 0,
      "inProgress": 0,
      "pending": 0
    },
    "changeRequests": 0,
    "changeRequestsBreakdown": {
      "new": 0,
      "assigned": 0,
      "inProgress": 0,
      "pending": 0
    },
    "serviceRequestsSla": 92,
    "incidentsResponseSla": 98,
    "incidentsResolutionSla": 94,
    "requestsResponseSla": 99,
    "requestsResolutionSla": 96,
    "activeIncidents": []
  },
  "cartridges": [
    {
      "type": "88A",
      "current": 85,
      "target": 100,
      "label": "HP LaserJet 88A"
    },
    {
      "type": "12A",
      "current": 34,
      "target": 50,
      "label": "HP LaserJet 12A"
    },
    {
      "type": "378A",
      "current": 28,
      "target": 40,
      "label": "Premium 378A Color"
    }
  ],
  "onboardingRequests": [
    {
      "id": "REQ-OB-01",
      "type": "onboarding",
      "employeeName": "Amit Kumar",
      "department": "Digital Transformation",
      "date": "2026-05-19"
    },
    {
      "id": "REQ-OB-02",
      "type": "onboarding",
      "employeeName": "Priya Sharma",
      "department": "HR Shared Services",
      "date": "2026-05-21"
    },
    {
      "id": "REQ-OF-01",
      "type": "offboarding",
      "employeeName": "Rajesh Patel",
      "department": "Finance & Accounts",
      "date": "2026-05-24"
    },
    {
      "id": "REQ-OB-03",
      "type": "onboarding",
      "employeeName": "Suresh Naidu",
      "department": "Operations",
      "date": "2026-05-25"
    }
  ]
}